{
   "$schema" : "http://json-schema.org/draft-04/schema#",
   "description" : "MT5 user password change receive",
   "type" : "object",
   "required" : [
      "msg_type",
      "echo_req"
   ],
   
   "title" : "MT5 user password change receive",
   "properties" : {
      "msg_type" : {
         "description" : "mt5_password_change",
         "type" : "string"
      },
      "echo_req" : {
         "title" : "Echo request",
         "description" : "Echo of the request made"
      },
      "mt5_password_change" : {
         "title" : "Password Change Status",
         "type" : "integer",
         "description" : "1 on success"
      },
      "req_id" : {
         "description" : "Optional field send in request to map to response, present only when request contains req_id",
         "type" : "integer"
      }
   }
}
