{
   "$schema" : "http://json-schema.org/draft-04/schema#",
   "required" : [
      "echo_req",
      "msg_type"
   ],
   "type" : "object",
   "description" : null,
   "title" : "Forget All Response",
   
   "properties" : {
      "msg_type" : {
         "type" : "string",
         "description" : "forget_all"
      },
      "forget_all" : {
         "type" : "array",
         "description" : "Ids of the cancelled streams"
      },
      "req_id" : {
         "type" : "integer",
         "description" : "Optional field send in request to map to response, present only when request contains req_id"
      },
      "echo_req" : {
         "title" : "Echo request",
         "description" : "Echo of the request made"
      }
   }
}
